davidkhala/gcp/pubsub/__init__.py
davidkhala/gcp/pubsub/__pycache__/__init__.cpython-312.pyc
davidkhala/gcp/pubsub/__pycache__/pub.cpython-312.pyc
davidkhala/gcp/pubsub/__pycache__/sub.cpython-312.pyc
davidkhala/gcp/pubsub/pub.py
davidkhala/gcp/pubsub/sub.py
davidkhala_gcp_pubsub-0.0.6.dist-info/METADATA
davidkhala_gcp_pubsub-0.0.6.dist-info/WHEEL
davidkhala_gcp_pubsub-0.0.6.dist-info/RECORD
