Metadata-Version: 2.3
Name: davidkhala.gcp.pubsub
Version: 0.0.6
Summary: @davidkhala/gcp/pubsub
Author: David Liu
Author-email: david-khala@hotmail.com
Requires-Python: >=3.10,<4.0
Classifier: Programming Language :: Python :: 3
Classifier: Programming Language :: Python :: 3.10
Classifier: Programming Language :: Python :: 3.11
Classifier: Programming Language :: Python :: 3.12
Classifier: Programming Language :: Python :: 3.13
Requires-Dist: davidkhala-gcp
Requires-Dist: google-cloud-pubsub
